pyarango_async/__init__.py
pyarango_async/arango_async.py
pyarango_async-0.0.3.dist-info/LICENSE
pyarango_async-0.0.3.dist-info/METADATA
pyarango_async-0.0.3.dist-info/WHEEL
pyarango_async-0.0.3.dist-info/top_level.txt
pyarango_async-0.0.3.dist-info/RECORD
