Metadata-Version: 2.1
Name: pyarango-async
Version: 0.0.3
Summary: A simple arango driver for python async codes
Home-page: https://github.com/JRafiei/pyarango-async
Author: MJR
Author-email: rafiei_mohamad@ymail.com
License: UNKNOWN
Platform: UNKNOWN
Classifier: Programming Language :: Python :: 3
Classifier: License :: OSI Approved :: MIT License
Classifier: Operating System :: OS Independent
Requires-Dist: aiohttp
Requires-Dist: async-timeout
